dynaflow/__init__.py
dynaflow/core/__init__.py
dynaflow/core/constants.py
dynaflow/core/executor.py
dynaflow/core/state_factory.py
dynaflow/core/logic/__init__.py
dynaflow/core/logic/conditions.py
dynaflow/core/schemas/__init__.py
dynaflow/core/schemas/bases.py
dynaflow/core/schemas/states.py
dynaflow/core/states/__init__.py
dynaflow/core/states/base.py
dynaflow/core/states/choice_state.py
dynaflow/core/states/exceptions.py
dynaflow/core/states/fail_state.py
dynaflow/core/states/map_state.py
dynaflow/core/states/parallel_state.py
dynaflow/core/states/pass_state.py
dynaflow/core/states/succeed_state.py
dynaflow/core/states/task_state.py
dynaflow/core/states/wait_state.py
dynaflow/utils/__init__.py
dynaflow/utils/data_manipulation.py
dynaflow/utils/validator.py
tests/test_schemas/__init__.py
tests/test_schemas/test_choice_state.py
tests/test_schemas/test_fail_state.py
tests/test_schemas/test_flow_schema.py
tests/test_schemas/test_map_state.py
tests/test_schemas/test_parallel_state.py
tests/test_schemas/test_pass_state.py
tests/test_schemas/test_succeed_state.py
tests/test_schemas/test_task_state.py
tests/test_schemas/test_wait_state.py
tests/test_states/__init__.py
tests/test_states/test_choise.py
tests/test_states/test_fail.py
tests/test_states/test_pass.py
tests/test_states/test_succeed.py
tests/test_states/test_task.py
tests/test_states/test_wait.py
py_dynaflow-1.0.0.dist-info/LICENSE
py_dynaflow-1.0.0.dist-info/METADATA
py_dynaflow-1.0.0.dist-info/WHEEL
py_dynaflow-1.0.0.dist-info/top_level.txt
py_dynaflow-1.0.0.dist-info/RECORD
