Metadata-Version: 2.1
Name: py-dynaflow
Version: 1.0.0
Summary: A Dynamic Workflow Execution Tool for Python 🚀
Home-page: https://github.com/sgg10/dynaflow
Author: sgg10
Author-email: sgg10.develop@gmail.com
License: MIT
Project-URL: Bug Reports, https://github.com/sgg10/dynaflow/issues
Project-URL: Source, https://github.com/sgg10/dynaflow/
Project-URL: Repository, https://github.com/sgg10/dynaflow/
Classifier: Development Status :: 3 - Alpha
Classifier: Topic :: Utilities
Classifier: License :: OSI Approved :: MIT License
Classifier: Programming Language :: Python :: 3
Classifier: Programming Language :: Python :: 3.9
Requires-Python: >=3.9
License-File: LICENSE
Requires-Dist: jsonpath-ng~=1.7.0
Requires-Dist: jsonschema~=4.23.0
Requires-Dist: jsonschema-specifications~=2024.10.1
Requires-Dist: referencing~=0.35.1
Provides-Extra: dev
Requires-Dist: pytest==8.3.4; extra == "dev"
